envier/__init__.py
envier/_version.py
envier/env.py
envier/mypy.py
envier/validators.py
envier-0.6.0.dist-info/METADATA
envier-0.6.0.dist-info/WHEEL
envier-0.6.0.dist-info/licenses/LICENSE
envier-0.6.0.dist-info/RECORD
