Metadata-Version: 2.3
Name: envier
Version: 0.6.0
Summary: Python application configuration via the environment
Project-URL: Homepage, https://github.com/DataDog/envier
Author-email: Datadog <dev@datadoghq.com>
License: MIT License
License-File: LICENSE
Classifier: License :: OSI Approved :: MIT License
Classifier: Programming Language :: Python
Classifier: Programming Language :: Python :: 3.7
Classifier: Programming Language :: Python :: 3.8
Classifier: Programming Language :: Python :: 3.9
Classifier: Programming Language :: Python :: 3.10
Classifier: Programming Language :: Python :: 3.11
Classifier: Programming Language :: Python :: 3.12
Classifier: Programming Language :: Python :: 3.13
Requires-Python: >=3.7
Provides-Extra: mypy
Requires-Dist: mypy; extra == 'mypy'
